{
  "data": [
    {
      "featureName": "Sạc nhanh 2h"
    },
    {
      "featureName": "Kết nối đa thiết bị"
    },
    {
      "featureName": "Click không tiếng"
    },
    {
      "featureName": "Đèn led thông báo tình trạng pin"
    },
    {
      "featureName": "Chống cháy nổ"
    },
    {
      "featureName": "Kháng nước"
    },
    {
      "featureName": "Chế độ tự cân chỉnh âm"
    },
    {
      "featureName": "Không dây"
    },
    {
      "featureName": "Nhận diện khuôn mặt"
    }
  ]
}